data/icon.png
data/models/bbox_model.pt
data/models/model.pt
deepbet/__init__.py
deepbet/bet.py
deepbet/ui/__init__.py
deepbet/ui/cli.py
deepbet/ui/gui.py
deepbet/utils.py
deepbet-1.0.2.dist-info/LICENSE
deepbet-1.0.2.dist-info/METADATA
deepbet-1.0.2.dist-info/WHEEL
deepbet-1.0.2.dist-info/entry_points.txt
deepbet-1.0.2.dist-info/RECORD
