Metadata-Version: 2.1
Name: deepbet
Version: 1.0.2
Summary: Fast brain extraction using neural networks
Home-page: https://github.com/wwu-mmll/deepbet
License: MIT
Author: codingfisch
Author-email: l_fisc17@wwu.de
Requires-Python: >=3.8,<4.0
Classifier: Intended Audience :: Science/Research
Classifier: License :: OSI Approved :: MIT License
Classifier: Operating System :: OS Independent
Classifier: Programming Language :: Python :: 3
Classifier: Programming Language :: Python :: 3.8
Classifier: Programming Language :: Python :: 3.9
Classifier: Programming Language :: Python :: 3.10
Classifier: Programming Language :: Python :: 3.11
Requires-Dist: connected-components-3d
Requires-Dist: customtkinter
Requires-Dist: fill_voids
Requires-Dist: nibabel
Requires-Dist: pandas
Requires-Dist: torch (>=1.11.0)
Requires-Dist: tqdm
Project-URL: Repository, https://github.com/wwu-mmll/deepbet
